{
    "record": [
        {
            "author": " KingSiong\n",
            "remark": " \"\u851a\u6765\u676f\"2022\u725b\u5ba2\u6691\u671f\u591a\u6821\u8bad\u7ec3\u84252 I \u9898\n",
            "source": "0_Link_with_Bracket_Sequence.html",
            "time": "2022-07-24 01:45:12",
            "title": "Link_with_Bracket_Sequence"
        },
        {
            "author": " KingSiong\n",
            "remark": " \"\u851a\u6765\u676f\"2022\u725b\u5ba2\u6691\u671f\u591a\u6821\u8bad\u7ec3\u84252 J \u9898\n",
            "source": "1_Link_with_Arithmetic_Progression.html",
            "time": "2022-07-24 01:48:04",
            "title": "Link_with_Arithmetic_Progression"
        },
        {
            "author": " KingSiong\n",
            "remark": " \"\u851a\u6765\u676f\"2022\u725b\u5ba2\u6691\u671f\u591a\u6821\u8bad\u7ec3\u84252 I \u9898\n",
            "source": "2_let_fat_tension.html",
            "time": "2022-07-24 01:50:20",
            "title": "let_fat_tension"
        }
    ]
}